circe_transformations/__init__.py
circe_transformations_certic-0.0.3.dist-info/METADATA
circe_transformations_certic-0.0.3.dist-info/WHEEL
circe_transformations_certic-0.0.3.dist-info/RECORD
