Metadata-Version: 2.1
Name: circe-transformations-certic
Version: 0.0.3
Summary: Circe tranformations library
License: Cecill
Author: Mickaël Desfrênes
Author-email: mickael.desfrenes@unicaen.fr
Requires-Python: >=3.9,<4.0
Classifier: License :: Other/Proprietary License
Classifier: Programming Language :: Python :: 3
Classifier: Programming Language :: Python :: 3.9
Classifier: Programming Language :: Python :: 3.10
Classifier: Programming Language :: Python :: 3.11
Requires-Dist: mammoth (>=1.4.19,<2.0.0)
Requires-Dist: markdown2 (>=2.4.3,<3.0.0)
Requires-Dist: pypandoc (>=1.8.1,<2.0.0)
Requires-Dist: weasyprint (>=55.0,<56.0)
